Metadata-Version: 2.1
Name: file-lines-counter
Version: 0.0.3
Summary: lines  counter
Author: me
Author-email: aa@example.com
Classifier: Programming Language :: Python :: 3
Classifier: License :: OSI Approved :: MIT License
Classifier: Operating System :: OS Independent
Requires-Python: >=3.7
